coloroma/__init__.py
coloroma/colors.py
coloroma-0.0.3.dist-info/LICENSE
coloroma-0.0.3.dist-info/METADATA
coloroma-0.0.3.dist-info/WHEEL
coloroma-0.0.3.dist-info/top_level.txt
coloroma-0.0.3.dist-info/RECORD
