Metadata-Version: 2.1
Name: coloroma
Version: 0.0.3
Summary: python package to handle colorful outputs
Home-page: https://github.com/tartley/colorama
Author: Turtley root
Author-email: turtley100@gmail.com
Classifier: Programming Language :: Python :: 3
Classifier: License :: OSI Approved :: MIT License
Classifier: Operating System :: OS Independent
Requires-Python: >=3.7
License-File: LICENSE
